spark_datax_tools/__init__.py
spark_datax_tools/functions/__init__.py
spark_datax_tools/functions/generator.py
spark_datax_tools/utils/__init__.py
spark_datax_tools/utils/files/base.html
spark_datax_tools/utils/files/bts.html
spark_datax_tools/utils/files/connect_direct.html
spark_datax_tools/utils/files/datax.html
spark_datax_tools/utils/files/elasticsearch.html
spark_datax_tools/utils/files/gcs.html
spark_datax_tools/utils/files/hdfs.html
spark_datax_tools/utils/files/oraclepe.html
spark_datax_tools/utils/files/saleforce.html
spark_datax_tools/utils/files/sftp.html
spark_datax_tools-0.7.0.dist-info/LICENSE
spark_datax_tools-0.7.0.dist-info/METADATA
spark_datax_tools-0.7.0.dist-info/WHEEL
spark_datax_tools-0.7.0.dist-info/top_level.txt
spark_datax_tools-0.7.0.dist-info/RECORD
